flask_script_exception_handler.py
flask_script_exception_handler-0.1.0.dist-info/RECORD
flask_script_exception_handler-0.1.0.dist-info/DESCRIPTION.rst
flask_script_exception_handler-0.1.0.dist-info/top_level.txt
flask_script_exception_handler-0.1.0.dist-info/METADATA
flask_script_exception_handler-0.1.0.dist-info/WHEEL
flask_script_exception_handler-0.1.0.dist-info/metadata.json
